data/__init__.py
data/data.py
datalibs/__init__.py
datalibs/data.py
datalibs-1.1.1.dist-info/LICENSE
datalibs-1.1.1.dist-info/LICENSE-APACHE
datalibs-1.1.1.dist-info/LICENSE-MIT
datalibs-1.1.1.dist-info/METADATA
datalibs-1.1.1.dist-info/WHEEL
datalibs-1.1.1.dist-info/top_level.txt
datalibs-1.1.1.dist-info/RECORD
